odoo/addons/account_manual_currency/README.rst
odoo/addons/account_manual_currency/__init__.py
odoo/addons/account_manual_currency/__manifest__.py
odoo/addons/account_manual_currency/data/decimal_data.xml
odoo/addons/account_manual_currency/i18n/account_manual_currency.pot
odoo/addons/account_manual_currency/i18n/it.po
odoo/addons/account_manual_currency/models/__init__.py
odoo/addons/account_manual_currency/models/account_move.py
odoo/addons/account_manual_currency/readme/CONTRIBUTORS.md
odoo/addons/account_manual_currency/readme/DESCRIPTION.md
odoo/addons/account_manual_currency/readme/USAGE.md
odoo/addons/account_manual_currency/static/description/icon.png
odoo/addons/account_manual_currency/static/description/index.html
odoo/addons/account_manual_currency/tests/__init__.py
odoo/addons/account_manual_currency/tests/test_account_manual_currency.py
odoo/addons/account_manual_currency/views/account_move_view.xml
odoo/addons/account_manual_currency/wizard/__init__.py
odoo/addons/account_manual_currency/wizard/account_payment_register.py
odoo/addons/account_manual_currency/wizard/account_payment_register_views.xml
odoo_addon_account_manual_currency-18.0.1.0.0.6.dist-info/METADATA
odoo_addon_account_manual_currency-18.0.1.0.0.6.dist-info/WHEEL
odoo_addon_account_manual_currency-18.0.1.0.0.6.dist-info/top_level.txt
odoo_addon_account_manual_currency-18.0.1.0.0.6.dist-info/RECORD
